marlo_sentiment/__init__.py
marlo_sentiment/client.py
marlo_sentiment/exceptions.py
marlo_sentiment/types.py
marlo_sentiment-1.0.4.dist-info/METADATA
marlo_sentiment-1.0.4.dist-info/WHEEL
marlo_sentiment-1.0.4.dist-info/RECORD
